README.md
setup.py
mock_mycroft_backend/__init__.py
mock_mycroft_backend/__main__.py
mock_mycroft_backend/configuration.py
mock_mycroft_backend/session.py
mock_mycroft_backend.egg-info/PKG-INFO
mock_mycroft_backend.egg-info/SOURCES.txt
mock_mycroft_backend.egg-info/dependency_links.txt
mock_mycroft_backend.egg-info/entry_points.txt
mock_mycroft_backend.egg-info/requires.txt
mock_mycroft_backend.egg-info/top_level.txt
mock_mycroft_backend/backend/__init__.py
mock_mycroft_backend/backend/auth.py
mock_mycroft_backend/backend/decorators.py
mock_mycroft_backend/backend/device.py
mock_mycroft_backend/backend/external_apis.py
mock_mycroft_backend/backend/precise.py
mock_mycroft_backend/backend/stt.py
mock_mycroft_backend/backend/tts.py
mock_mycroft_backend/database/__init__.py
mock_mycroft_backend/database/metrics.py
mock_mycroft_backend/database/utterances.py
mock_mycroft_backend/database/wakewords.py
mock_mycroft_backend/utils/__init__.py
mock_mycroft_backend/utils/geolocate.py