Metadata-Version: 1.0
Name: mock-mycroft-backend
Version: 0.3.0
Summary: mock mycroft backend
Home-page: https://github.com/OpenJarbas/mock-backend
Author: jarbasAI
Author-email: jarbasai@mailfence.com
License: Apache-2.0
Platform: UNKNOWN
